apb_protocol/apb_slave.v
// APB Slave Module
module apb_slave(
    input clk,
    input rst_n,
    
    // APB Signals
    input [31:0] paddr,
    input penable,
    input pwrite,
    input [31:0] pwdata,
    output reg [31:0] prdata,
    output reg pready,
    input psel
);

    // Internal Memory for Slave
    reg [31:0] slave_memory [0:255];
    
    // State encoding using standard Verilog
    reg [1:0] current_state;
    reg [1:0] next_state;

    // State definitions
    parameter IDLE   = 2'b00;
    parameter SETUP  = 2'b01;
    parameter ACCESS = 2'b10;

    integer i; // For memory initialization

    // State Register
    always @(posedge clk or negedge rst_n) begin
        if (!rst_n) begin
            current_state <= IDLE;
            prdata <= 32'h0;
            pready <= 1'b0;
            
            // Initialize memory
            for (i = 0; i < 256; i = i + 1) begin
                slave_memory[i] <= 32'h0;
            end
        end else begin
            current_state <= next_state;
        end
    end

    // Next State Logic
    always @(*) begin
        case (current_state)
            IDLE: begin
                if (psel && !penable) begin
                    next_state = SETUP;
                    pready = 1'b0;
                end else begin
                    next_state = IDLE;
                    pready = 1'b0;
                end
            end

            SETUP: begin
                next_state = ACCESS;
                pready = 1'b0;
            end

            ACCESS: begin
                next_state = IDLE;
                pready = 1'b1;

                // Write Operation
                if (pwrite) begin
                    slave_memory[paddr[9:2]] = pwdata;
                end
                
                // Read Operation
                if (!pwrite) begin
                    prdata = slave_memory[paddr[9:2]];
                end
            end

            default: begin
                next_state = IDLE;
                pready = 1'b0;
            end
        endcase
    end

endmodule

apb_protocol/apb_master.v
// APB Master Module
module apb_master(
    input clk,
    input rst_n,
    
    // APB Signals
    output reg [31:0] paddr,
    output reg penable,
    output reg pwrite,
    output reg [31:0] pwdata,
    input [31:0] prdata,
    input pready,
    output reg psel
);

    // State encoding using standard Verilog
    reg [1:0] current_state;
    reg [1:0] next_state;

    // State definitions
    parameter IDLE   = 2'b00;
    parameter SETUP  = 2'b01;
    parameter ACCESS = 2'b10;

    // Registers for transaction
    reg [31:0] data_to_write;
    reg [31:0] read_data;

    // State Register
    always @(posedge clk or negedge rst_n) begin
        if (!rst_n) begin
            current_state <= IDLE;
            paddr <= 32'h0;
            penable <= 1'b0;
            pwrite <= 1'b0;
            psel <= 1'b0;
            pwdata <= 32'h0;
        end else begin
            current_state <= next_state;
        end
    end

    // Next State Logic
    always @(*) begin
        case (current_state)
            IDLE: begin
                next_state = SETUP;
                paddr = 32'h1000;  // Example address
                pwrite = 1'b1;     // Write operation
                data_to_write = 32'hA5A5A5A5;  // Example data
                psel = 1'b1;
                penable = 1'b0;
            end

            SETUP: begin
                next_state = ACCESS;
                penable = 1'b1;
                pwdata = data_to_write;
            end

            ACCESS: begin
                if (pready) begin
                    // For read, capture data
                    if (!pwrite) begin
                        read_data = prdata;
                    end
                    
                    // Return to IDLE
                    next_state = IDLE;
                    psel = 1'b0;
                    penable = 1'b0;
                end else begin
                    // Wait for slave
                    next_state = ACCESS;
                end
            end

            default: begin
                next_state = IDLE;
            end
        endcase
    end

endmodule

apb_protocol/apb_protocol_top.v
// Top-level module for APB Protocol demonstration
module apb_protocol_top(
    input clk,
    input rst_n,
    
    // APB Master Signals
    output [31:0] paddr,      // Address
    output penable,           // Enable
    output pwrite,            // Write/Read select
    output [31:0] pwdata,     // Write data
    input [31:0] prdata,      // Read data
    input pready,             // Slave ready signal
    output psel                // Select signal
);

    // Instantiate APB Master
    apb_master master (
        .clk(clk),
        .rst_n(rst_n),
        .paddr(paddr),
        .penable(penable),
        .pwrite(pwrite),
        .pwdata(pwdata),
        .prdata(prdata),
        .pready(pready),
        .psel(psel)
    );

    // Instantiate APB Slave
    apb_slave slave (
        .clk(clk),
        .rst_n(rst_n),
        .paddr(paddr),
        .penable(penable),
        .pwrite(pwrite),
        .pwdata(pwdata),
        .prdata(prdata),
        .pready(pready),
        .psel(psel)
    );

endmodule

apb_protocol/apb_protocol_tb.v
// Testbench for APB Protocol
`timescale 1ns/1ps

module apb_protocol_tb;
    // Signals
    reg clk;
    reg rst_n;
    wire [31:0] paddr;
    wire penable;
    wire pwrite;
    wire [31:0] pwdata;
    wire [31:0] prdata;
    wire pready;
    wire psel;

    // Instantiate Top Module
    apb_protocol_top dut (
        .clk(clk),
        .rst_n(rst_n),
        .paddr(paddr),
        .penable(penable),
        .pwrite(pwrite),
        .pwdata(pwdata),
        .prdata(prdata),
        .pready(pready),
        .psel(psel)
    );

    // Clock Generation
    always #5 clk = ~clk;

    // Testbench Stimulus
    initial begin
        // Initialize Signals
        clk = 0;
        rst_n = 0;

        // Reset Sequence
        #10 rst_n = 1;

        // Simulation will run automatically based on master's state machine
        #200 $finish;
    end

    // Optional Waveform Capture
    initial begin
        $dumpfile("apb_protocol_tb.vcd");
        $dumpvars(0, apb_protocol_tb);
    
endmodule

apb_protocol_tb.vcd
$date
	Fri Apr 18 08:49:09 2025
$end
$version
	Icarus Verilog
$end
$timescale
	1ps
$end
$scope module apb_protocol_tb $end
$var wire 1 ! pwrite $end
$var wire 32 " pwdata [31:0] $end
$var wire 1 # psel $end
$var wire 1 $ pready $end
$var wire 32 % prdata [31:0] $end
$var wire 1 & penable $end
$var wire 32 ' paddr [31:0] $end
$var reg 1 ( clk $end
$var reg 1 ) rst_n $end
$scope module dut $end
$var wire 1 ( clk $end
$var wire 1 ) rst_n $end
$var wire 1 ! pwrite $end
$var wire 32 * pwdata [31:0] $end
$var wire 1 # psel $end
$var wire 1 $ pready $end
$var wire 32 + prdata [31:0] $end
$var wire 1 & penable $end
$var wire 32 , paddr [31:0] $end
$scope module master $end
$var wire 1 ( clk $end
$var wire 1 ) rst_n $end
$var wire 1 $ pready $end
$var wire 32 - prdata [31:0] $end
$var reg 2 . current_state [1:0] $end
$var reg 32 / data_to_write [31:0] $end
$var reg 2 0 next_state [1:0] $end
$var reg 32 1 paddr [31:0] $end
$var reg 1 & penable $end
$var reg 1 # psel $end
$var reg 32 2 pwdata [31:0] $end
$var reg 1 ! pwrite $end
$var reg 32 3 read_data [31:0] $end
$upscope $end
$scope module slave $end
$var wire 1 ( clk $end
$var wire 32 4 paddr [31:0] $end
$var wire 1 & penable $end
$var wire 1 # psel $end
$var wire 32 5 pwdata [31:0] $end
$var wire 1 ! pwrite $end
$var wire 1 ) rst_n $end
$var reg 2 6 current_state [1:0] $end
$var reg 2 7 next_state [1:0] $end
$var reg 32 8 prdata [31:0] $end
$var reg 1 $ pready $end
$var integer 32 9 i [31:0] $end
$upscope $end
$upscope $end
$upscope $end
$enddefinitions $end
#0
$dumpvars
b100000000 9
b0 8
b1 7
b0 6
b0 5
b1000000000000 4
bx 3
b0 2
b1000000000000 1
b1 0
b10100101101001011010010110100101 /
b0 .
b0 -
b1000000000000 ,
b0 +
b0 *
0)
0(
b1000000000000 '
0&
b0 %
0$
1#
b0 "
1!
$end
#5000
b1 7
1#
1!
b1000000000000 '
b1000000000000 ,
b1000000000000 1
b1000000000000 4
b100000000 9
1(
#10000
0(
1)
#15000
b10100101101001011010010110100101 "
b10100101101001011010010110100101 *
b10100101101001011010010110100101 2
b10100101101001011010010110100101 5
1&
b10 0
b10 7
b1 .
b1 6
1(
#20000
0(
#25000
0&
0#
b0 0
1$
b0 7
b10 6
b10 .
1(
#30000
0(
#35000
b1 7
1#
b1 0
0$
b0 .
b0 6
1(
#40000
0(
#45000
b10 7
1&
b10 0
b1 6
b1 .
1(
#50000
0(
#55000
0&
0#
b0 0
1$
b0 7
b10 .
b10 6
1(
#60000
0(
#65000
0$
b1 7
1#
b1 0
b0 6
b0 .
1(
#70000
0(
#75000
1&
b10 0
b10 7
b1 .
b1 6
1(
#80000
0(
#85000
0&
0#
b0 0
1$
b0 7
b10 6
b10 .
1(
#90000
0(
#95000
b1 7
1#
b1 0
0$
b0 .
b0 6
1(
#100000
0(
#105000
b10 7
1&
b10 0
b1 6
b1 .
1(
#110000
0(
#115000
0&
0#
b0 0
1$
b0 7
b10 .
b10 6
1(
#120000
0(
#125000
0$
b1 7
1#
b1 0
b0 6
b0 .
1(
#130000
0(
#135000
1&
b10 0
b10 7
b1 .
b1 6
1(
#140000
0(
#145000
0&
0#
b0 0
1$
b0 7
b10 6
b10 .
1(
#150000
0(
#155000
b1 7
1#
b1 0
0$
b0 .
b0 6
1(
#160000
0(
#165000
b10 7
1&
b10 0
b1 6
b1 .
1(
#170000
0(
#175000
0&
0#
b0 0
1$
b0 7
b10 .
b10 6
1(
#180000
0(
#185000
0$
b1 7
1#
b1 0
b0 6
b0 .
1(
#190000
0(
#195000
1&
b10 0
b10 7
b1 .
b1 6
1(
#200000
0(
#205000
0&
0#
b0 0
1$
b0 7
b10 6
b10 .
1(
